phm_feature/__init__.py
phm_feature/torchphm/__init__.py
phm_feature/torchphm/beta_hpss.py
phm_feature/torchphm/functional.py
phm_feature/torchphm/layers.py
phm_feature-0.1.1.dist-info/LICENSE
phm_feature-0.1.1.dist-info/METADATA
phm_feature-0.1.1.dist-info/WHEEL
phm_feature-0.1.1.dist-info/top_level.txt
phm_feature-0.1.1.dist-info/RECORD
