Metadata-Version: 2.1
Name: phm-feature
Version: 0.1.1
Summary: time-freq feature from signal for phm purpose
Home-page: UNKNOWN
Author: QinHaiNing
Author-email: 2364839934@qq.com
License: UNKNOWN
Platform: UNKNOWN
Classifier: Programming Language :: Python :: 3
Classifier: License :: OSI Approved :: MIT License
Classifier: Operating System :: OS Independent
